banner_esther/__init__.py
banner_esther/banner.py
banner_esther-0.3.0.dist-info/METADATA
banner_esther-0.3.0.dist-info/WHEEL
banner_esther-0.3.0.dist-info/entry_points.txt
banner_esther-0.3.0.dist-info/top_level.txt
banner_esther-0.3.0.dist-info/RECORD
