Metadata-Version: 2.1
Name: banner_esther
Version: 0.3.0
Summary: Banner Output Program
Author-email: EstherCho-7 <dkgkqm777@gmail.com>
License: MIT
Project-URL: Homepage, https://github.com/EstherCho-7/banner_esther
Project-URL: Issues, https://github.com/EstherCho-7/banner_esther/issues
Requires-Python: >=3.9
Requires-Dist: pyfiglet >=1.0.2
